Sem 4/Computer Organization and Architecture (CS2007)/Labs/CS23I1027/Lab7/Q2/full_adder.v
module full_adder (
    input A,        // First input bit
    input B,        // Second input bit
    input C,        // Third input bit
    output sum,     // Sum output
    output carry    // Carry output
);

    assign sum0 = A ^ B;     // Sum0 is the XOR of the two inputs
    assign sum = sum0 ^ C; // Sum1 is the XOR of the three inputs
    
    assign carry0 = A & B;
    assign carry1 = (A ^ B) & C;
    assign carry = (carry1 | carry0);    // Carry is the overall carry.

endmodule

Sem 4/Computer Organization and Architecture (CS2007)/Labs/CS23I1027/Lab7/Q2/tb_full_adder.v
module tb_full_adder;

    reg A;        // First input
    reg B;        // Second input
    reg C;        // Carry-in input
    wire sum;     // Sum output
    wire carry;   // Carry output

    // Instantiate the Full Adder module
    full_adder uut (
        .A(A), 
        .B(B),
        .C(C),
        .sum(sum), 
        .carry(carry)
    );

    // Test stimulus
    initial begin
        $dumpfile("full_adder.vcd");
        $dumpvars(0, tb_full_adder);

        // Test all combinations of inputs
        A = 0; B = 0; C = 0; #10;  // Test case: 0 + 0 + 0
        A = 0; B = 0; C = 1; #10;  // Test case: 0 + 0 + 1
        A = 0; B = 1; C = 0; #10;  // Test case: 0 + 1 + 0
        A = 0; B = 1; C = 1; #10;  // Test case: 0 + 1 + 1
        A = 1; B = 0; C = 0; #10;  // Test case: 1 + 0 + 0
        A = 1; B = 0; C = 1; #10;  // Test case: 1 + 0 + 1
        A = 1; B = 1; C = 0; #10;  // Test case: 1 + 1 + 0
        A = 1; B = 1; C = 1; #10;  // Test case: 1 + 1 + 1

        $finish;  // End the simulation
    end

    // Monitor the signals
    initial begin
        $monitor("Time = %0t | A = %b | B = %b | C = %b | sum = %b | carry = %b", $time, A, B, C, sum, carry);
    end

endmodule

Sem 4/Computer Organization and Architecture (CS2007)/Labs/CS23I1027/Lab7/Q2/full_adder.vcd
$date
	Mon Mar 10 17:19:13 2025
$end
$version
	Icarus Verilog
$end
$timescale
	1s
$end
$scope module tb_full_adder $end
$var wire 1 ! sum $end
$var wire 1 " carry $end
$var reg 1 # A $end
$var reg 1 $ B $end
$var reg 1 % C $end
$scope module uut $end
$var wire 1 # A $end
$var wire 1 $ B $end
$var wire 1 % C $end
$var wire 1 " carry $end
$var wire 1 & carry0 $end
$var wire 1 ' carry1 $end
$var wire 1 ! sum $end
$var wire 1 ( sum0 $end
$upscope $end
$upscope $end
$enddefinitions $end
#0
$dumpvars
0(
0'
0&
0%
0$
0#
0"
0!
$end
#10
1!
1%
#20
1(
0%
1$
#30
1"
0!
1'
1%
#40
0"
1!
0'
0%
0$
1#
#50
1"
0!
1'
1%
#60
0'
0(
1&
0%
1$
#70
1!
1%
