Sem 4/Computer Organization and Architecture (CS2007)/Labs/CS23I1027/Lab8/Q1/counter.v
module counter (
    input clk,           // Clock input
    input reset,         // Reset input
    output [3:0] count   // 4-bit count output
);
    reg [3:0] count_reg; // Register to hold the current count

    // Counter logic
    always @(posedge clk or posedge reset) begin
        if (reset) begin
            count_reg <= 4'b0000;  // Reset the counter to 0
        end else if (count_reg == 4'b1001) begin
            count_reg <= 4'b0000;  // Reset the counter to 0 when it reaches 9
        end else begin
            count_reg <= count_reg + 1; // Increment the counter otherwise
        end
    end

    assign count = count_reg; // Assign the current count
endmodule

Sem 4/Computer Organization and Architecture (CS2007)/Labs/CS23I1027/Lab8/Q1/tb_counter.v
module tb_counter;

    reg clk;           // Clock signal
    reg reset;         // Reset signal
    wire [3:0] count;  // 4-bit counter output

    // Instantiate the counter module
    counter uut (
        .clk(clk),
        .reset(reset),
        .count(count)
    );

    // Generate clock signal
    always begin
        #5 clk = ~clk; // Toggle clock every 5 time units
    end

    // Test stimulus
    initial begin
        $dumpfile("counter.vcd");
        $dumpvars(0, tb_counter);

        // Initialize signals
        clk = 0;
        reset = 1;    // Initially
        #10 reset = 0; // Reset after 10 time units

        // Simulate for 100 time units to observe the counter's behavior
        #100;

        $finish; // End the simulation
    end

    // Monitor the signals
    initial begin
        $monitor("Time = %0t | reset = %b | count = %d", $time, reset, count);
    end

endmodule

Sem 4/Computer Organization and Architecture (CS2007)/Labs/CS23I1027/Lab8/Q1/counter.vcd
$date
	Mon Mar 17 16:25:35 2025
$end
$version
	Icarus Verilog
$end
$timescale
	1s
$end
$scope module tb_counter $end
$var wire 4 ! count [3:0] $end
$var reg 1 " clk $end
$var reg 1 # reset $end
$scope module uut $end
$var wire 1 " clk $end
$var wire 4 $ count [3:0] $end
$var wire 1 # reset $end
$var reg 4 % count_reg [3:0] $end
$upscope $end
$upscope $end
$enddefinitions $end
#0
$dumpvars
b0 %
b0 $
1#
0"
b0 !
$end
#5
1"
#10
0"
0#
#15
b1 !
b1 $
b1 %
1"
#20
0"
#25
b10 !
b10 $
b10 %
1"
#30
0"
#35
b11 !
b11 $
b11 %
1"
#40
0"
#45
b100 !
b100 $
b100 %
1"
#50
0"
#55
b101 !
b101 $
b101 %
1"
#60
0"
#65
b110 !
b110 $
b110 %
1"
#70
0"
#75
b111 !
b111 $
b111 %
1"
#80
0"
#85
b1000 !
b1000 $
b1000 %
1"
#90
0"
#95
b1001 !
b1001 $
b1001 %
1"
#100
0"
#105
b0 !
b0 $
b0 %
1"
