Sem 4/Computer Organization and Architecture (CS2007)/Labs/CS23I1027/Lab8/Q2/seven_segment.v
module seven_segment (
    input [3:0] digit,    // 4-bit input to select a digit (0-9)
    output reg a,         // Segment a
    output reg b,         // Segment b
    output reg c,         // Segment c
    output reg d,         // Segment d
    output reg e,         // Segment e
    output reg f,         // Segment f
    output reg g          // Segment g
);

    // Logic to decode the input digit into the seven segment display
    always @ (digit) begin
        case (digit)
            4'b0000: begin // 0
                a = 1; b = 1; c = 1; d = 1; e = 1; f = 1; g = 0;
            end
            4'b0001: begin // 1
                a = 0; b = 1; c = 1; d = 0; e = 0; f = 0; g = 0;
            end
            4'b0010: begin // 2
                a = 1; b = 1; c = 0; d = 1; e = 1; f = 0; g = 1;
            end
            4'b0011: begin // 3
                a = 1; b = 1; c = 1; d = 1; e = 0; f = 0; g = 1;
            end
            4'b0100: begin // 4
                a = 0; b = 1; c = 1; d = 0; e = 0; f = 1; g = 1;
            end
            4'b0101: begin // 5
                a = 1; b = 0; c = 1; d = 1; e = 0; f = 1; g = 1;
            end
            4'b0110: begin // 6
                a = 1; b = 0; c = 1; d = 1; e = 1; f = 1; g = 1;
            end
            4'b0111: begin // 7
                a = 1; b = 1; c = 1; d = 0; e = 0; f = 0; g = 0;
            end
            4'b1000: begin // 8
                a = 1; b = 1; c = 1; d = 1; e = 1; f = 1; g = 1;
            end
            4'b1001: begin // 9
                a = 1; b = 1; c = 1; d = 1; e = 0; f = 1; g = 1;
            end
            default: begin
                a = 0; b = 0; c = 0; d = 0; e = 0; f = 0; g = 0; // Default to all off
            end
        endcase
    end

endmodule

Sem 4/Computer Organization and Architecture (CS2007)/Labs/CS23I1027/Lab8/Q2/tb_seven_segment.v
module tb_seven_segment;

    reg [3:0] digit;   // 4-bit input to select a digit
    wire a, b, c, d, e, f, g;  // Seven segment outputs

    // Instantiate the seven_segment module
    seven_segment uut (
        .digit(digit),
        .a(a), .b(b), .c(c), .d(d), .e(e), .f(f), .g(g)
    );

    // Stimulus block
    initial begin
	    $dumpfile("seven_segment.vcd");
        $dumpvars(0, tb_seven_segment);
        
        // Display digits 0 to 9
        digit = 4'b0000; #10;  // Display 0
        digit = 4'b0001; #10;  // Display 1
        digit = 4'b0010; #10;  // Display 2
        digit = 4'b0011; #10;  // Display 3
        digit = 4'b0100; #10;  // Display 4
        digit = 4'b0101; #10;  // Display 5
        digit = 4'b0110; #10;  // Display 6
        digit = 4'b0111; #10;  // Display 7
        digit = 4'b1000; #10;  // Display 8
        digit = 4'b1001; #10;  // Display 9

        $finish;  // End simulation
    end

    // Monitor the signals
    initial begin
        $monitor("Time = %0t | digit = %d | a = %b | b = %b | c = %b | d = %b | e = %b | f = %b | g = %b", 
                 $time, digit, a, b, c, d, e, f, g);
    end

endmodule

Sem 4/Computer Organization and Architecture (CS2007)/Labs/CS23I1027/Lab8/Q2/seven_segment.vcd
$date
	Mon Mar 17 16:36:44 2025
$end
$version
	Icarus Verilog
$end
$timescale
	1s
$end
$scope module tb_seven_segment $end
$var wire 1 ! g $end
$var wire 1 " f $end
$var wire 1 # e $end
$var wire 1 $ d $end
$var wire 1 % c $end
$var wire 1 & b $end
$var wire 1 ' a $end
$var reg 4 ( digit [3:0] $end
$scope module uut $end
$var wire 4 ) digit [3:0] $end
$var reg 1 ' a $end
$var reg 1 & b $end
$var reg 1 % c $end
$var reg 1 $ d $end
$var reg 1 # e $end
$var reg 1 " f $end
$var reg 1 ! g $end
$upscope $end
$upscope $end
$enddefinitions $end
#0
$dumpvars
b0 )
b0 (
1'
1&
1%
1$
1#
1"
0!
$end
#10
0"
0#
0$
0'
b1 (
b1 )
#20
1!
1#
1$
0%
1'
b10 (
b10 )
#30
0#
1%
b11 (
b11 )
#40
1"
0$
0'
b100 (
b100 )
#50
1$
0&
1'
b101 (
b101 )
#60
1#
b110 (
b110 )
#70
0!
0"
0#
0$
1&
b111 (
b111 )
#80
1!
1"
1#
1$
b1000 (
b1000 )
#90
0#
b1001 (
b1001 )
