Sem 4/Computer Organization and Architecture (CS2007)/Labs/CS23I1027/Lab8/Q3/ss_counter.v
module ss_counter (
    input clk,                // Clock input
    input reset,              // Reset input
    output [3:0] count,       // 4-bit count output
    output reg [6:0] segments // 7-segment display output (changed to reg)
);

    reg [3:0] count_reg; // Register to hold the current count

    // Counter logic
    always @(posedge clk or posedge reset) begin
        if (reset) begin
            count_reg <= 4'b0000;  // Reset the counter to 0
        end else if (count_reg == 4'b1001) begin
            count_reg <= 4'b0000;  // Reset the counter to 0 when it reaches 9
        end else begin
            count_reg <= count_reg + 1; // Increment the counter otherwise
        end
    end

    assign count = count_reg; // Keep track of the current count

    // 7-segment display logic using case statements
    always @(*) begin
        case (count_reg)
            4'b0000: segments = 7'b1111110; // Display '0'
            4'b0001: segments = 7'b0110000; // Display '1'
            4'b0010: segments = 7'b1101101; // Display '2'
            4'b0011: segments = 7'b1111001; // Display '3'
            4'b0100: segments = 7'b0110011; // Display '4'
            4'b0101: segments = 7'b1011011; // Display '5'
            4'b0110: segments = 7'b1011111; // Display '6'
            4'b0111: segments = 7'b1110000; // Display '7'
            4'b1000: segments = 7'b1111111; // Display '8'
            4'b1001: segments = 7'b1111011; // Display '9'
            default: segments = 7'b0000000; // Blank display
        endcase
    end

endmodule

Sem 4/Computer Organization and Architecture (CS2007)/Labs/CS23I1027/Lab8/Q3/tb_ss_counter.v
module tb_ss_counter;

    reg clk;           // Clock signal
    reg reset;         // Reset signal
    wire [3:0] count;  // 4-bit counter output
    wire [6:0] segments; // 7-segment display output

    // Instantiate the counter module
    ss_counter uut (
        .clk(clk),
        .reset(reset),
        .count(count),
        .segments(segments)
    );

    // Generate clock signal
    always begin
        #5 clk = ~clk; // Toggle clock every 5 time units
    end

    // Test stimulus
    initial begin
        $dumpfile("ss_counter.vcd");
        $dumpvars(0, tb_ss_counter);

        // Initialize signals
        clk = 0;
        reset = 1;    // Apply reset initially
        #10 reset = 0; // Release reset after 10 time units

        // Simulate for 100 time units to observe the counter's behavior
        #100;

        $finish; // End the simulation
    end

    // Monitor the signals
    initial begin
        $monitor("Time = %0t | reset = %b | count = %d | segments = %b",
                 $time, reset, count, segments);
    end

endmodule

Sem 4/Computer Organization and Architecture (CS2007)/Labs/CS23I1027/Lab8/Q3/ss_counter.vcd
$date
	Mon Mar 17 17:01:33 2025
$end
$version
	Icarus Verilog
$end
$timescale
	1s
$end
$scope module tb_ss_counter $end
$var wire 7 ! segments [6:0] $end
$var wire 4 " count [3:0] $end
$var reg 1 # clk $end
$var reg 1 $ reset $end
$scope module uut $end
$var wire 1 # clk $end
$var wire 4 % count [3:0] $end
$var wire 1 $ reset $end
$var reg 4 & count_reg [3:0] $end
$var reg 7 ' segments [6:0] $end
$upscope $end
$upscope $end
$enddefinitions $end
#0
$dumpvars
b1111110 '
b0 &
b0 %
1$
0#
b0 "
b1111110 !
$end
#5
1#
#10
0#
0$
#15
b110000 !
b110000 '
b1 "
b1 %
b1 &
1#
#20
0#
#25
b1101101 !
b1101101 '
b10 "
b10 %
b10 &
1#
#30
0#
#35
b1111001 !
b1111001 '
b11 "
b11 %
b11 &
1#
#40
0#
#45
b110011 !
b110011 '
b100 "
b100 %
b100 &
1#
#50
0#
#55
b1011011 !
b1011011 '
b101 "
b101 %
b101 &
1#
#60
0#
#65
b1011111 !
b1011111 '
b110 "
b110 %
b110 &
1#
#70
0#
#75
b1110000 !
b1110000 '
b111 "
b111 %
b111 &
1#
#80
0#
#85
b1111111 !
b1111111 '
b1000 "
b1000 %
b1000 &
1#
#90
0#
#95
b1111011 !
b1111011 '
b1001 "
b1001 %
b1001 &
1#
#100
0#
#105
b1111110 !
b1111110 '
b0 "
b0 %
b0 &
1#
